python_semrush/__init__.py
python_semrush/errors.py
python_semrush/semrush.py
python_semrush/tests/__init__.py
python_semrush/tests/response.txt
python_semrush/tests/test_semrush.py
python_semrush-0.1.5.dist-info/LICENSE
python_semrush-0.1.5.dist-info/WHEEL
python_semrush-0.1.5.dist-info/METADATA
python_semrush-0.1.5.dist-info/RECORD
